src/Alert_System.py
src/__init__.py
TestMonitoringSystem-0.1.0.dist-info/METADATA
TestMonitoringSystem-0.1.0.dist-info/WHEEL
TestMonitoringSystem-0.1.0.dist-info/top_level.txt
TestMonitoringSystem-0.1.0.dist-info/RECORD
