Metadata-Version: 2.1
Name: TestMonitoringSystem
Version: 0.1.0
Summary: TestMonitoringSystem
Home-page: https://github.com/yuta0726/TestMonitoringSystem
Author: yuta morimoto
Author-email: s2222081@stu.musashino-u.ac.jp
Requires-Python: >=3.12.3
